spotmax/__init__.py
spotmax/__main__.py
spotmax/_debug.py
spotmax/_process.py
spotmax/_process_watchdog.py
spotmax/_run.py
spotmax/_version.py
spotmax/_warnings.py
spotmax/colors.py
spotmax/config.py
spotmax/core.py
spotmax/data.py
spotmax/dialogs.py
spotmax/features.py
spotmax/filters.py
spotmax/gui.py
spotmax/html_func.py
spotmax/io.py
spotmax/palettes.py
spotmax/pipe.py
spotmax/prompts.py
spotmax/qtworkers.py
spotmax/resources.qrc
spotmax/scores.py
spotmax/transformations.py
spotmax/tune.py
spotmax/utils.py
spotmax/widgets.py
spotmax/BioImageIO/__init__.py
spotmax/BioImageIO/create_model_resource.ipynb
spotmax/BioImageIO/model.py
spotmax/BioImageIO/test_any_model_gui.py
spotmax/BioImageIO/test_any_model_script.py
spotmax/BioImageIO/SpotMAX_UNet_3D/README.md
spotmax/BioImageIO/SpotMAX_UNet_3D/_sphere_3d.svg
spotmax/BioImageIO/SpotMAX_UNet_3D/config.yaml
spotmax/BioImageIO/SpotMAX_UNet_3D/cover.png
spotmax/BioImageIO/SpotMAX_UNet_3D/cover.svg
spotmax/BioImageIO/SpotMAX_UNet_3D/create_3d_sphere_surface.py
spotmax/BioImageIO/SpotMAX_UNet_3D/create_cover_image.py
spotmax/BioImageIO/SpotMAX_UNet_3D/create_io_samples.py
spotmax/BioImageIO/SpotMAX_UNet_3D/environment.yml
spotmax/BioImageIO/SpotMAX_UNet_3D/input_sample.npy
spotmax/BioImageIO/SpotMAX_UNet_3D/model_usage.py
spotmax/BioImageIO/SpotMAX_UNet_3D/output_sample_mask.npy
spotmax/Spotiflow/__init__.py
spotmax/Spotiflow/spotiflow_smax_model.py
spotmax/docs/Makefile
spotmax/docs/__init__.py
spotmax/docs/make.bat
spotmax/docs/requirements.txt
spotmax/docs/source/__init__.py
spotmax/docs/source/conf.py
spotmax/docs/source/index.rst
spotmax/docs/source/api/api.rst
spotmax/docs/source/features/_background_description.rst
spotmax/docs/source/features/_effect_size_Cohen_formula.rst
spotmax/docs/source/features/_effect_size_Glass_formula.rst
spotmax/docs/source/features/_effect_size_Hedge_formula.rst
spotmax/docs/source/features/_effect_size_description.rst
spotmax/docs/source/features/aggr_features_description.rst
spotmax-1.1.9.dist-info/licenses/LICENSE
spotmax-1.1.9.dist-info/METADATA
spotmax-1.1.9.dist-info/WHEEL
spotmax-1.1.9.dist-info/entry_points.txt
spotmax-1.1.9.dist-info/top_level.txt
spotmax-1.1.9.dist-info/RECORD
