Metadata-Version: 2.4
Name: spotmax
Version: 1.1.9
Summary: Automatic 3D detection and quantification of fluorescent objects
Author-email: Francesco Padovani <francesco.padovani@helmholtz-munich.de>
License-Expression: BSD-3-Clause
Project-URL: Homepage, https://github.com/ElpadoCan/SpotMAX
Project-URL: Author contact, https://schmollerlab.com/francescopadovani
Project-URL: Schmoller lab, https://schmollerlab.com/
Keywords: 3D fluorescent signal analysis,image analysis
Classifier: Development Status :: 3 - Alpha
Classifier: Programming Language :: Python :: 3 :: Only
Classifier: Programming Language :: Python :: 3.10
Classifier: Programming Language :: Python :: 3.11
Classifier: Programming Language :: Python :: 3.12
Classifier: Intended Audience :: Education
Classifier: Intended Audience :: Science/Research
Classifier: Operating System :: Microsoft :: Windows
Classifier: Operating System :: POSIX
Classifier: Operating System :: Unix
Classifier: Operating System :: MacOS
Classifier: Topic :: Scientific/Engineering
Classifier: Topic :: Scientific/Engineering :: Bio-Informatics
Classifier: Topic :: Scientific/Engineering :: Information Analysis
Classifier: Topic :: Scientific/Engineering :: Image Processing
Classifier: Topic :: Scientific/Engineering :: Visualization
Classifier: Topic :: Utilities
Requires-Python: >=3.10
License-File: LICENSE
Requires-Dist: PyYAML
Provides-Extra: all
Requires-Dist: cellacdc; extra == "all"
Requires-Dist: numba; extra == "all"
Requires-Dist: torch; extra == "all"
Requires-Dist: pyyaml; extra == "all"
Requires-Dist: pytorch3dunet-spotmax; extra == "all"
Requires-Dist: wandb; extra == "all"
Requires-Dist: bioimageio.core; extra == "all"
Requires-Dist: bioimageio.spec; extra == "all"
Provides-Extra: biio
Requires-Dist: bioimageio.core; extra == "biio"
Requires-Dist: bioimageio.spec; extra == "biio"
Dynamic: license-file
